{"edges": [[0, 1], [0, 2], [0, 3], [0, 4], [1, 2], [1, 3], [2, 3], [2, 5], [2, 4], [3, 5], [3, 4]], "features": {"0": "0", "1": "1", "2": "2", "3": "3", "4": "4", "5": "5"}, "count": 2, "cite": 17, "position": 3.0, "connect": 1.5, "totalConnect": 4.0, "totalCount": 0.5, "totalCite": 10.0, "totalPosition": 3.6666666666666665, "name": "Hentschel,Bernd", "nodes": [{"id": "0"}, {"id": "1"}, {"id": "2"}, {"id": "3"}, {"id": "4"}, {"id": "5"}], "edgess": [{"source": "0", "target": "1"}, {"source": "0", "target": "2"}, {"source": "0", "target": "3"}, {"source": "0", "target": "4"}, {"source": "1", "target": "2"}, {"source": "1", "target": "3"}, {"source": "2", "target": "3"}, {"source": "2", "target": "5"}, {"source": "2", "target": "4"}, {"source": "3", "target": "5"}, {"source": "3", "target": "4"}], "year": 2016, "authorId": {"0": "Hentschel,Bernd", "1": "Pick,Sebastian", "2": "Weyers,Benjamin", "3": "Kuhlen,TorstenW.", "4": "Haenel,Claudia", "5": "Freitag,Sebastian"}}